arbo/__init__.py
arbo/__version__.py
arbo/api.py
arbo/formatters.py
arbo/handlers.py
arbo-0.0.2.dist-info/DESCRIPTION.rst
arbo-0.0.2.dist-info/METADATA
arbo-0.0.2.dist-info/RECORD
arbo-0.0.2.dist-info/WHEEL
arbo-0.0.2.dist-info/metadata.json
arbo-0.0.2.dist-info/top_level.txt
